{
    "DOWN": {
        "precision": 0.5922401171303074,
        "recall": 0.6372587632926349,
        "f1-score": 0.6139252513754506,
        "support": 2539.0
    },
    "UP": {
        "precision": 0.36041666666666666,
        "recall": 0.3178199632578077,
        "f1-score": 0.3377806703547022,
        "support": 1633.0
    },
    "accuracy": 0.5122243528283796,
    "macro avg": {
        "precision": 0.4763283918984871,
        "recall": 0.4775393632752213,
        "f1-score": 0.47585296086507645,
        "support": 4172.0
    },
    "weighted avg": {
        "precision": 0.5015000177518019,
        "recall": 0.5122243528283796,
        "f1-score": 0.5058370201178086,
        "support": 4172.0
    }
}