{
    "DOWN": {
        "precision": 0.8453666856168277,
        "recall": 0.6521929824561403,
        "f1-score": 0.7363208715028473,
        "support": 2280.0
    },
    "UP": {
        "precision": 0.34136212624584716,
        "recall": 0.6017569546120058,
        "f1-score": 0.43561208267090623,
        "support": 683.0
    },
    "accuracy": 0.6405669929125886,
    "macro avg": {
        "precision": 0.5933644059313374,
        "recall": 0.6269749685340731,
        "f1-score": 0.5859664770868768,
        "support": 2963.0
    },
    "weighted avg": {
        "precision": 0.7291887868485591,
        "recall": 0.6405669929125886,
        "f1-score": 0.6670046032705774,
        "support": 2963.0
    }
}