{
    "DOWN": {
        "precision": 0.7208307880268784,
        "recall": 0.3765156349712827,
        "f1-score": 0.4946552085516663,
        "support": 3134.0
    },
    "UP": {
        "precision": 0.280559646539028,
        "recall": 0.6251025430680885,
        "f1-score": 0.3872935196950445,
        "support": 1219.0
    },
    "accuracy": 0.4461291063634275,
    "macro avg": {
        "precision": 0.5006952172829532,
        "recall": 0.5008090890196857,
        "f1-score": 0.4409743641233554,
        "support": 4353.0
    },
    "weighted avg": {
        "precision": 0.597538685689711,
        "recall": 0.4461291063634275,
        "f1-score": 0.4645899894576571,
        "support": 4353.0
    }
}