{
    "DOWN": {
        "precision": 0.7142857142857143,
        "recall": 0.6463414634146342,
        "f1-score": 0.678617157490397,
        "support": 410.0
    },
    "UP": {
        "precision": 0.28217821782178215,
        "recall": 0.3496932515337423,
        "f1-score": 0.31232876712328766,
        "support": 163.0
    },
    "accuracy": 0.5619546247818499,
    "macro avg": {
        "precision": 0.4982319660537482,
        "recall": 0.49801735747418824,
        "f1-score": 0.49547296230684235,
        "support": 573.0
    },
    "weighted avg": {
        "precision": 0.5913650826563585,
        "recall": 0.5619546247818499,
        "f1-score": 0.5744199364959139,
        "support": 573.0
    }
}