{
    "DOWN": {
        "precision": 0.7419962335216572,
        "recall": 0.39478957915831664,
        "f1-score": 0.5153695225637671,
        "support": 998.0
    },
    "UP": {
        "precision": 0.3333333333333333,
        "recall": 0.6879271070615034,
        "f1-score": 0.44907063197026026,
        "support": 439.0
    },
    "accuracy": 0.48434237995824636,
    "macro avg": {
        "precision": 0.5376647834274952,
        "recall": 0.54135834310991,
        "f1-score": 0.48222007726701366,
        "support": 1437.0
    },
    "weighted avg": {
        "precision": 0.6171507128656557,
        "recall": 0.48434237995824636,
        "f1-score": 0.4951153729670034,
        "support": 1437.0
    }
}