{
    "DOWN": {
        "precision": 0.7816091954022989,
        "recall": 0.4726911618669315,
        "f1-score": 0.5891089108910892,
        "support": 2014.0
    },
    "UP": {
        "precision": 0.3244274809160305,
        "recall": 0.6572164948453608,
        "f1-score": 0.43441226575809205,
        "support": 776.0
    },
    "accuracy": 0.5240143369175627,
    "macro avg": {
        "precision": 0.5530183381591647,
        "recall": 0.5649538283561462,
        "f1-score": 0.5117605883245906,
        "support": 2790.0
    },
    "weighted avg": {
        "precision": 0.6544504102978744,
        "recall": 0.5240143369175627,
        "f1-score": 0.5460821737501552,
        "support": 2790.0
    }
}