{
    "DOWN": {
        "precision": 0.9150401836969001,
        "recall": 0.22077562326869807,
        "f1-score": 0.355724168712341,
        "support": 3610.0
    },
    "UP": {
        "precision": 0.1320580067880284,
        "recall": 0.852589641434263,
        "f1-score": 0.22869356131445367,
        "support": 502.0
    },
    "accuracy": 0.29790856031128404,
    "macro avg": {
        "precision": 0.5235490952424643,
        "recall": 0.5366826323514805,
        "f1-score": 0.2922088650133974,
        "support": 4112.0
    },
    "weighted avg": {
        "precision": 0.8194523790256323,
        "recall": 0.29790856031128404,
        "f1-score": 0.3402160546768985,
        "support": 4112.0
    }
}