{
    "DOWN": {
        "precision": 0.7272727272727273,
        "recall": 0.32333767926988266,
        "f1-score": 0.447653429602888,
        "support": 767.0
    },
    "UP": {
        "precision": 0.38066825775656327,
        "recall": 0.7742718446601942,
        "f1-score": 0.5104000000000001,
        "support": 412.0
    },
    "accuracy": 0.48091603053435117,
    "macro avg": {
        "precision": 0.5539704925146453,
        "recall": 0.5488047619650385,
        "f1-score": 0.47902671480144404,
        "support": 1179.0
    },
    "weighted avg": {
        "precision": 0.6061522510719982,
        "recall": 0.48091603053435117,
        "f1-score": 0.4695801361369085,
        "support": 1179.0
    }
}