{
    "DOWN": {
        "precision": 0.7673627974745022,
        "recall": 0.730804810360777,
        "f1-score": 0.7486377635631366,
        "support": 2162.0
    },
    "UP": {
        "precision": 0.3821656050955414,
        "recall": 0.42908224076281287,
        "f1-score": 0.4042672655811342,
        "support": 839.0
    },
    "accuracy": 0.6464511829390204,
    "macro avg": {
        "precision": 0.5747642012850218,
        "recall": 0.579943525561795,
        "f1-score": 0.5764525145721354,
        "support": 3001.0
    },
    "weighted avg": {
        "precision": 0.6596718796451292,
        "recall": 0.6464511829390204,
        "f1-score": 0.652360906579831,
        "support": 3001.0
    }
}