{
    "DOWN": {
        "precision": 0.5202312138728323,
        "recall": 0.3614457831325301,
        "f1-score": 0.42654028436018954,
        "support": 249.0
    },
    "UP": {
        "precision": 0.4820846905537459,
        "recall": 0.6406926406926406,
        "f1-score": 0.5501858736059481,
        "support": 231.0
    },
    "accuracy": 0.49583333333333335,
    "macro avg": {
        "precision": 0.5011579522132892,
        "recall": 0.5010692119125854,
        "f1-score": 0.4883630789830688,
        "support": 480.0
    },
    "weighted avg": {
        "precision": 0.501873199525522,
        "recall": 0.49583333333333335,
        "f1-score": 0.48604472418471084,
        "support": 480.0
    }
}