{
    "DOWN": {
        "precision": 0.75,
        "recall": 0.2845220030349014,
        "f1-score": 0.41254125412541254,
        "support": 1318.0
    },
    "UP": {
        "precision": 0.29257314328582146,
        "recall": 0.7572815533980582,
        "f1-score": 0.42207792207792205,
        "support": 515.0
    },
    "accuracy": 0.41734860883797054,
    "macro avg": {
        "precision": 0.5212865716429107,
        "recall": 0.5209017782164798,
        "f1-score": 0.4173095881016673,
        "support": 1833.0
    },
    "weighted avg": {
        "precision": 0.6214812704812864,
        "recall": 0.41734860883797054,
        "f1-score": 0.41522067801823437,
        "support": 1833.0
    }
}