{
    "DOWN": {
        "precision": 0.6675041876046901,
        "recall": 0.8569892473118279,
        "f1-score": 0.7504708097928436,
        "support": 930.0
    },
    "UP": {
        "precision": 0.4291845493562232,
        "recall": 0.2012072434607646,
        "f1-score": 0.27397260273972607,
        "support": 497.0
    },
    "accuracy": 0.6285914505956552,
    "macro avg": {
        "precision": 0.5483443684804566,
        "recall": 0.5290982453862962,
        "f1-score": 0.5122217062662848,
        "support": 1427.0
    },
    "weighted avg": {
        "precision": 0.584501482482414,
        "recall": 0.6285914505956552,
        "f1-score": 0.5845145316531103,
        "support": 1427.0
    }
}