{
    "DOWN": {
        "precision": 0.7248280175109444,
        "recall": 0.5400745573159367,
        "f1-score": 0.6189586114819761,
        "support": 2146.0
    },
    "UP": {
        "precision": 0.4018181818181818,
        "recall": 0.6010879419764279,
        "f1-score": 0.48165637486378493,
        "support": 1103.0
    },
    "accuracy": 0.5607879347491536,
    "macro avg": {
        "precision": 0.5633230996645631,
        "recall": 0.5705812496461823,
        "f1-score": 0.5503074931728805,
        "support": 3249.0
    },
    "weighted avg": {
        "precision": 0.6151697076404867,
        "recall": 0.5607879347491536,
        "f1-score": 0.5723460023746,
        "support": 3249.0
    }
}