{
    "DOWN": {
        "precision": 0.72400513478819,
        "recall": 0.3477188655980271,
        "f1-score": 0.46980424822990424,
        "support": 1622.0
    },
    "UP": {
        "precision": 0.31432274789371356,
        "recall": 0.6928571428571428,
        "f1-score": 0.432456531431119,
        "support": 700.0
    },
    "accuracy": 0.4517657192075797,
    "macro avg": {
        "precision": 0.5191639413409518,
        "recall": 0.520288004227585,
        "f1-score": 0.4511303898305116,
        "support": 2322.0
    },
    "weighted avg": {
        "precision": 0.6005005392558327,
        "recall": 0.4517657192075797,
        "f1-score": 0.45854524661097673,
        "support": 2322.0
    }
}