{
    "DOWN": {
        "precision": 0.9862398202752036,
        "recall": 0.9720453916412953,
        "f1-score": 0.9790911625313632,
        "support": 3613.0
    },
    "UP": {
        "precision": 0.13675213675213677,
        "recall": 0.24615384615384617,
        "f1-score": 0.17582417582417584,
        "support": 65.0
    },
    "accuracy": 0.9592169657422512,
    "macro avg": {
        "precision": 0.5614959785136702,
        "recall": 0.6090996188975708,
        "f1-score": 0.5774576691777695,
        "support": 3678.0
    },
    "weighted avg": {
        "precision": 0.9712271233124522,
        "recall": 0.9592169657422512,
        "f1-score": 0.9648953076819975,
        "support": 3678.0
    }
}