{
    "DOWN": {
        "precision": 0.6852505292872265,
        "recall": 0.3481534600215131,
        "f1-score": 0.4617213504517356,
        "support": 2789.0
    },
    "UP": {
        "precision": 0.2733812949640288,
        "recall": 0.6053097345132743,
        "f1-score": 0.3766519823788546,
        "support": 1130.0
    },
    "accuracy": 0.42230160755294716,
    "macro avg": {
        "precision": 0.47931591212562763,
        "recall": 0.47673159726739367,
        "f1-score": 0.4191866664152951,
        "support": 3919.0
    },
    "weighted avg": {
        "precision": 0.5664926229883713,
        "recall": 0.42230160755294716,
        "f1-score": 0.4371925456744058,
        "support": 3919.0
    }
}