{
    "DOWN": {
        "precision": 0.8042328042328042,
        "recall": 0.16050686378035903,
        "f1-score": 0.2676056338028169,
        "support": 947.0
    },
    "UP": {
        "precision": 0.21209117938553024,
        "recall": 0.852589641434263,
        "f1-score": 0.33968253968253975,
        "support": 251.0
    },
    "accuracy": 0.3055091819699499,
    "macro avg": {
        "precision": 0.5081619918091672,
        "recall": 0.506548252607311,
        "f1-score": 0.3036440867426783,
        "support": 1198.0
    },
    "weighted avg": {
        "precision": 0.6801697425995273,
        "recall": 0.3055091819699499,
        "f1-score": 0.28270688870750005,
        "support": 1198.0
    }
}