{
    "DOWN": {
        "precision": 0.7183098591549296,
        "recall": 0.37777777777777777,
        "f1-score": 0.4951456310679612,
        "support": 135.0
    },
    "UP": {
        "precision": 0.5227272727272727,
        "recall": 0.8214285714285714,
        "f1-score": 0.6388888888888888,
        "support": 112.0
    },
    "accuracy": 0.5789473684210527,
    "macro avg": {
        "precision": 0.6205185659411012,
        "recall": 0.5996031746031746,
        "f1-score": 0.567017259978425,
        "support": 247.0
    },
    "weighted avg": {
        "precision": 0.6296246377788262,
        "recall": 0.5789473684210527,
        "f1-score": 0.5603247601203656,
        "support": 247.0
    }
}