{
    "DOWN": {
        "precision": 0.6836310252018596,
        "recall": 0.9872791519434629,
        "f1-score": 0.8078646812201822,
        "support": 2830.0
    },
    "UP": {
        "precision": 0.4782608695652174,
        "recall": 0.024886877828054297,
        "f1-score": 0.047311827956989246,
        "support": 1326.0
    },
    "accuracy": 0.6802213666987488,
    "macro avg": {
        "precision": 0.5809459473835386,
        "recall": 0.5060830148857586,
        "f1-score": 0.42758825458858574,
        "support": 4156.0
    },
    "weighted avg": {
        "precision": 0.6181062835333833,
        "recall": 0.6802213666987488,
        "f1-score": 0.5652051327536293,
        "support": 4156.0
    }
}