{
    "DOWN": {
        "precision": 0.6519270988945324,
        "recall": 0.7823592685550377,
        "f1-score": 0.711212516297262,
        "support": 2789.0
    },
    "UP": {
        "precision": 0.4251893939393939,
        "recall": 0.2781908302354399,
        "f1-score": 0.33632958801498125,
        "support": 1614.0
    },
    "accuracy": 0.5975471269588917,
    "macro avg": {
        "precision": 0.5385582464169631,
        "recall": 0.5302750493952388,
        "f1-score": 0.5237710521561216,
        "support": 4403.0
    },
    "weighted avg": {
        "precision": 0.5688122554247178,
        "recall": 0.5975471269588917,
        "f1-score": 0.5737923377263782,
        "support": 4403.0
    }
}