{
    "DOWN": {
        "precision": 0.6502347417840375,
        "recall": 0.24732142857142858,
        "f1-score": 0.35834411384217335,
        "support": 1120.0
    },
    "UP": {
        "precision": 0.3661654135338346,
        "recall": 0.7657232704402516,
        "f1-score": 0.4954221770091556,
        "support": 636.0
    },
    "accuracy": 0.43507972665148065,
    "macro avg": {
        "precision": 0.508200077658936,
        "recall": 0.5065223495058401,
        "f1-score": 0.42688314542566447,
        "support": 1756.0
    },
    "weighted avg": {
        "precision": 0.5473485841717772,
        "recall": 0.43507972665148065,
        "f1-score": 0.4079919772671168,
        "support": 1756.0
    }
}