{
    "DOWN": {
        "precision": 0.6666666666666666,
        "recall": 0.04914933837429111,
        "f1-score": 0.09154929577464789,
        "support": 529.0
    },
    "UP": {
        "precision": 0.36005089058524176,
        "recall": 0.956081081081081,
        "f1-score": 0.5231053604436229,
        "support": 296.0
    },
    "accuracy": 0.37454545454545457,
    "macro avg": {
        "precision": 0.5133587786259541,
        "recall": 0.502615209727686,
        "f1-score": 0.3073273281091354,
        "support": 825.0
    },
    "weighted avg": {
        "precision": 0.556656642763513,
        "recall": 0.37454545454545457,
        "f1-score": 0.24638638079527406,
        "support": 825.0
    }
}